{
    "plugins":[
        "node_modules/better-docs/typescript",
        "node_modules/better-docs/category"
    ],
    "source":{
        "include":["src"],
        "includePattern": "\\.(jsx|js|ts|tsx)$",
        "excludePattern":"(node_modules|public)"
    },
    "templates":{
        "cleverLinks":false,
        "monospaceLinks":false
    },
    "opts":{
        "recurse":"true",
        "destination":"./documentation",
        "template":"node_modules/better-docs",
        "tutorials":"./tutorials"
    },
    "tags":{
        "allowUnknownTags": true
    }
}